<?xml version="1.0" encoding="UTF-8"?>
<modulo nombre="mod_cliente" descripcion="Cliente" permiso="0">
    <vista nombre="ListaClientes.php" descripcion="Listadoclientes" permiso="0">
        <accion nombre="crear" descripcion="Crear Cliente" permiso="0"></accion>
        <accion nombre="modificar" descripcion="Modificar Cliente" permiso="0"></accion>
	<accion nombre="ver" descripcion="Ver Cliente" permiso="0"></accion>
	<accion nombre="tarifa" descripcion="Ver Tarifas" permiso="0"></accion>
    </vista>
    <vista nombre="cliente.php" descripcion="Cliente" permiso="0"></vista>

</modulo>
